dash_cute_charts/BarChart.py
dash_cute_charts/LineChart.py
dash_cute_charts/PieChart.py
dash_cute_charts/RadarChart.py
dash_cute_charts/ScatterChart.py
dash_cute_charts/StackedChart.py
dash_cute_charts/__init__.py
dash_cute_charts/_imports_.py
dash_cute_charts/dash_cute_charts.min.js
dash_cute_charts/dash_cute_charts.min.js.map
dash_cute_charts/metadata.json
dash_cute_charts/package-info.json
dash_cute_charts-0.0.4.dist-info/LICENSE
dash_cute_charts-0.0.4.dist-info/METADATA
dash_cute_charts-0.0.4.dist-info/WHEEL
dash_cute_charts-0.0.4.dist-info/top_level.txt
dash_cute_charts-0.0.4.dist-info/RECORD
