Metadata-Version: 2.1
Name: dash-cute-charts
Version: 0.0.4
Summary: A cutechart integration for DashPlotly
Home-page: https://github.com/muntakim1/dash_cute_charts
Author: muntakim <muntakim.cse@gmail.com>
License: MIT
Platform: UNKNOWN
Classifier: Framework :: Dash
